README.md
pyproject.toml
setup.cfg
setup.py
RubikCipherX/__init__.py
RubikCipherX/client.py
RubikCipherX.egg-info/PKG-INFO
RubikCipherX.egg-info/SOURCES.txt
RubikCipherX.egg-info/dependency_links.txt
RubikCipherX.egg-info/requires.txt
RubikCipherX.egg-info/top_level.txt
RubikCipherX/crypto/__init__.py
RubikCipherX/crypto/crypto.py
RubikCipherX/gadgets/__init__.py
RubikCipherX/gadgets/classino.py
RubikCipherX/gadgets/exceptions.py
RubikCipherX/gadgets/methods.py
RubikCipherX/network/__init__.py
RubikCipherX/network/connection.py
RubikCipherX/network/proxies.py
RubikCipherX/sessions/__init__.py
RubikCipherX/sessions/sqliteSession.py
RubikCipherX/sessions/stringSession.py
RubikCipherX/structs/__init__.py
RubikCipherX/structs/handlers.py
RubikCipherX/structs/models.py
RubikCipherX/structs/results.py
RubikCipherX/structs/struct.py
RubikCipherX/met.json